{
    "dev": {
        "awscloudformation": {
            "AuthRoleName": "amplify-forwardslash-dev-131937-authRole",
            "UnauthRoleArn": "arn:aws:iam::633157192990:role/amplify-forwardslash-dev-131937-unauthRole",
            "AuthRoleArn": "arn:aws:iam::633157192990:role/amplify-forwardslash-dev-131937-authRole",
            "Region": "us-east-1",
            "DeploymentBucketName": "amplify-forwardslash-dev-131937-deployment",
            "UnauthRoleName": "amplify-forwardslash-dev-131937-unauthRole",
            "StackName": "amplify-forwardslash-dev-131937",
            "StackId": "arn:aws:cloudformation:us-east-1:633157192990:stack/amplify-forwardslash-dev-131937/b404d780-2389-11eb-a393-12c9c271ca70",
            "AmplifyAppId": "dc9r71x7o9c57"
        },
        "categories": {
            "hosting": {
                "amplifyhosting": {
                    "appId": "dc9r71x7o9c57",
                    "type": "manual"
                }
            }
        }
    }
}